{"sec":{"301":"Title-9/Chapter-3/9-301.xml","302":"Title-9/Chapter-3/9-302.xml","303":"Title-9/Chapter-3/9-303.xml","304":"Title-9/Chapter-3/9-304.xml","305":"Title-9/Chapter-3/9-305.xml","306":"Title-9/Chapter-3/9-306.xml","307":"Title-9/Chapter-3/9-307.xml","308":"Title-9/Chapter-3/9-308.xml","309":"Title-9/Chapter-3/9-309.xml","310":"Title-9/Chapter-3/9-310.xml","311":"Title-9/Chapter-3/9-311.xml","312":"Title-9/Chapter-3/9-312.xml","313":"Title-9/Chapter-3/9-313.xml","314":"Title-9/Chapter-3/9-314.xml","315":"Title-9/Chapter-3/9-315.xml","316":"Title-9/Chapter-3/9-316.xml","317":"Title-9/Chapter-3/9-317.xml","318":"Title-9/Chapter-3/9-318.xml","319":"Title-9/Chapter-3/9-319.xml","320":"Title-9/Chapter-3/9-320.xml","321":"Title-9/Chapter-3/9-321.xml","322":"Title-9/Chapter-3/9-322.xml","323":"Title-9/Chapter-3/9-323.xml","324":"Title-9/Chapter-3/9-324.xml","325":"Title-9/Chapter-3/9-325.xml","326":"Title-9/Chapter-3/9-326.xml","501":"Title-9/Chapter-5/9-501.xml","502":"Title-9/Chapter-5/9-502.xml","503":"Title-9/Chapter-5/9-503.xml","504":"Title-9/Chapter-5/9-504.xml","505":"Title-9/Chapter-5/9-505.xml","506":"Title-9/Chapter-5/9-506.xml","507":"Title-9/Chapter-5/9-507.xml","508":"Title-9/Chapter-5/9-508.xml","509":"Title-9/Chapter-5/9-509.xml","510":"Title-9/Chapter-5/9-510.xml","601":"Title-9/Chapter-6/9-601.xml","602":"Title-9/Chapter-6/9-602.xml","603":"Title-9/Chapter-6/9-603.xml","604":"Title-9/Chapter-6/9-604.xml","605":"Title-9/Chapter-6/9-605.xml","606":"Title-9/Chapter-6/9-606.xml","607":"Title-9/Chapter-6/9-607.xml","631":"Title-9/Chapter-6A/9-631.xml","632":"Title-9/Chapter-6A/9-632.xml","633":"Title-9/Chapter-6A/9-633.xml","634":"Title-9/Chapter-6A/9-634.xml","701":"Title-9/Chapter-7/9-701.xml","702":"Title-9/Chapter-7/9-702.xml","703":"Title-9/Chapter-7/9-703.xml","704":"Title-9/Chapter-7/9-704.xml","705":"Title-9/Chapter-7/9-705.xml","706":"Title-9/Chapter-7/9-706.xml","707":"Title-9/Chapter-7/9-707.xml","801":"Title-9/Chapter-8/9-801.xml","802":"Title-9/Chapter-8/9-802.xml","803":"Title-9/Chapter-8/9-803.xml","804":"Title-9/Chapter-8/9-804.xml","805":"Title-9/Chapter-8/9-805.xml","806":"Title-9/Chapter-8/9-806.xml","807":"Title-9/Chapter-8/9-807.xml","808":"Title-9/Chapter-8/9-808.xml","809":"Title-9/Chapter-8/9-809.xml","810":"Title-9/Chapter-8/9-810.xml","811":"Title-9/Chapter-8/9-811.xml","812":"Title-9/Chapter-8/9-812.xml","813":"Title-9/Chapter-8/9-813.xml","901":"Title-9/Chapter-9/9-901.xml","902":"Title-9/Chapter-9/9-902.xml","903":"Title-9/Chapter-9/9-903.xml","904":"Title-9/Chapter-9/9-904.xml","905":"Title-9/Chapter-9/9-905.xml","906":"Title-9/Chapter-9/9-906.xml","907":"Title-9/Chapter-9/9-907.xml","908":"Title-9/Chapter-9/9-908.xml","909":"Title-9/Chapter-9/9-909.xml","910":"Title-9/Chapter-9/9-910.xml","911":"Title-9/Chapter-9/9-911.xml","912":"Title-9/Chapter-9/9-912.xml","913":"Title-9/Chapter-9/9-913.xml","914":"Title-9/Chapter-9/9-914.xml","915":"Title-9/Chapter-9/9-915.xml","916":"Title-9/Chapter-9/9-916.xml","917":"Title-9/Chapter-9/9-917.xml","918":"Title-9/Chapter-9/9-918.xml","919":"Title-9/Chapter-9/9-919.xml","920":"Title-9/Chapter-9/9-920.xml","921":"Title-9/Chapter-9/9-921.xml","922":"Title-9/Chapter-9/9-922.xml","923":"Title-9/Chapter-9/9-923.xml","924":"Title-9/Chapter-9/9-924.xml","925":"Title-9/Chapter-9/9-925.xml","926":"Title-9/Chapter-9/9-926.xml","1001":"Title-9/Chapter-10/9-1001.xml","1002":"Title-9/Chapter-10/9-1002.xml","1003":"Title-9/Chapter-10/9-1003.xml","1004":"Title-9/Chapter-10/9-1004.xml","1005":"Title-9/Chapter-10/9-1005.xml","1006":"Title-9/Chapter-10/9-1006.xml","1007":"Title-9/Chapter-10/9-1007.xml","1008":"Title-9/Chapter-10/9-1008.xml","1009":"Title-9/Chapter-10/9-1009.xml","1010":"Title-9/Chapter-10/9-1010.xml","1011":"Title-9/Chapter-10/9-1011.xml","1151":"Title-9/Chapter-11A/9-1151.xml","1152":"Title-9/Chapter-11A/9-1152.xml","1153":"Title-9/Chapter-11A/9-1153.xml","1154":"Title-9/Chapter-11A/9-1154.xml","1155":"Title-9/Chapter-11A/9-1155.xml","1156":"Title-9/Chapter-11A/9-1156.xml","1157":"Title-9/Chapter-11A/9-1157.xml","1158":"Title-9/Chapter-11A/9-1158.xml","1159":"Title-9/Chapter-11A/9-1159.xml","1160":"Title-9/Chapter-11A/9-1160.xml","1161":"Title-9/Chapter-11A/9-1161.xml","1171":"Title-9/Chapter-11B/9-1171.xml","1172":"Title-9/Chapter-11B/9-1172.xml","1173":"Title-9/Chapter-11B/9-1173.xml","1174":"Title-9/Chapter-11B/9-1174.xml","101.01":"Title-9/Chapter-1/Subchapter-I/9-101.01.xml","101.02":"Title-9/Chapter-1/Subchapter-I/9-101.02.xml","101.03":"Title-9/Chapter-1/Subchapter-I/9-101.03.xml","101.04":"Title-9/Chapter-1/Subchapter-I/9-101.04~P.xml","101.05":"Title-9/Chapter-1/Subchapter-I/9-101.05.xml","101.06":"Title-9/Chapter-1/Subchapter-I/9-101.06.xml","101.07":"Title-9/Chapter-1/Subchapter-I/9-101.07.xml","101.08":"Title-9/Chapter-1/Subchapter-I/9-101.08.xml","101.09":"Title-9/Chapter-1/Subchapter-I/9-101.09.xml","101.10":"Title-9/Chapter-1/Subchapter-I/9-101.10.xml","101.11":"Title-9/Chapter-1/Subchapter-I/9-101.11.xml","101.12":"Title-9/Chapter-1/Subchapter-I/9-101.12.xml","101.13":"Title-9/Chapter-1/Subchapter-I/9-101.13.xml","101.14":"Title-9/Chapter-1/Subchapter-I/9-101.14.xml","101.15":"Title-9/Chapter-1/Subchapter-I/9-101.15.xml","101.16":"Title-9/Chapter-1/Subchapter-I/9-101.16.xml","101.17":"Title-9/Chapter-1/Subchapter-I/9-101.17.xml","101.18":"Title-9/Chapter-1/Subchapter-I/9-101.18.xml","109.01":"Title-9/Chapter-1/Subchapter-V/9-109.01.xml","109.02":"Title-9/Chapter-1/Subchapter-V/9-109.02.xml","109.03":"Title-9/Chapter-1/Subchapter-V/9-109.03.xml","111.01":"Title-9/Chapter-1/Subchapter-VI/9-111.01.xml","111.01a":"Title-9/Chapter-1/Subchapter-VI/9-111.01a.xml","111.01b":"Title-9/Chapter-1/Subchapter-VI/9-111.01b.xml","111.01c":"Title-9/Chapter-1/Subchapter-VI/9-111.01c.xml","111.31":"Title-9/Chapter-1/Subchapter-VI-A/9-111.31.xml","113.01":"Title-9/Chapter-1/Subchapter-VII/9-113.01~P.xml","113.02":"Title-9/Chapter-1/Subchapter-VII/9-113.02~P.xml","113.03":"Title-9/Chapter-1/Subchapter-VII/9-113.03~P.xml","113.04":"Title-9/Chapter-1/Subchapter-VII/9-113.04~P.xml","113.05":"Title-9/Chapter-1/Subchapter-VII/9-113.05~P.xml","113.06":"Title-9/Chapter-1/Subchapter-VII/9-113.06~P.xml","103.01":"Title-9/Chapter-1/Subchapter-II/9-103.01.xml","103.02":"Title-9/Chapter-1/Subchapter-II/9-103.02.xml","103.03":"Title-9/Chapter-1/Subchapter-II/9-103.03.xml","103.04":"Title-9/Chapter-1/Subchapter-II/9-103.04.xml","103.05":"Title-9/Chapter-1/Subchapter-II/9-103.05~P.xml","103.06":"Title-9/Chapter-1/Subchapter-II/9-103.06.xml","105.01":"Title-9/Chapter-1/Subchapter-III/9-105.01.xml","105.02":"Title-9/Chapter-1/Subchapter-III/9-105.02.xml","105.03":"Title-9/Chapter-1/Subchapter-III/9-105.03.xml","105.04":"Title-9/Chapter-1/Subchapter-III/9-105.04.xml","425.01":"Title-9/Chapter-4/Subchapter-III-A/9-425.01.xml","425.02":"Title-9/Chapter-4/Subchapter-III-A/9-425.02.xml","425.03":"Title-9/Chapter-4/Subchapter-III-A/9-425.03.xml","411.01":"Title-9/Chapter-4/Subchapter-II/9-411.01.xml","411.02":"Title-9/Chapter-4/Subchapter-II/9-411.02.xml","411.03":"Title-9/Chapter-4/Subchapter-II/9-411.03.xml","411.04":"Title-9/Chapter-4/Subchapter-II/9-411.04.xml","401.01":"Title-9/Chapter-4/Subchapter-I/9-401.01.xml","401.02":"Title-9/Chapter-4/Subchapter-I/9-401.02.xml","401.03":"Title-9/Chapter-4/Subchapter-I/9-401.03.xml","401.04":"Title-9/Chapter-4/Subchapter-I/9-401.04.xml","401.05":"Title-9/Chapter-4/Subchapter-I/9-401.05.xml","401.06":"Title-9/Chapter-4/Subchapter-I/9-401.06.xml","401.07":"Title-9/Chapter-4/Subchapter-I/9-401.07.xml","401.08":"Title-9/Chapter-4/Subchapter-I/9-401.08.xml","401.09":"Title-9/Chapter-4/Subchapter-I/9-401.09.xml","401.10":"Title-9/Chapter-4/Subchapter-I/9-401.10.xml","401.11":"Title-9/Chapter-4/Subchapter-I/9-401.11.xml","401.12":"Title-9/Chapter-4/Subchapter-I/9-401.12.xml","401.13":"Title-9/Chapter-4/Subchapter-I/9-401.13.xml","401.14":"Title-9/Chapter-4/Subchapter-I/9-401.14.xml","401.15":"Title-9/Chapter-4/Subchapter-I/9-401.15.xml","401.16":"Title-9/Chapter-4/Subchapter-I/9-401.16.xml","401.17":"Title-9/Chapter-4/Subchapter-I/9-401.17.xml","401.18":"Title-9/Chapter-4/Subchapter-I/9-401.18.xml","421.01":"Title-9/Chapter-4/Subchapter-III/9-421.01.xml","421.02":"Title-9/Chapter-4/Subchapter-III/9-421.02.xml","421.03":"Title-9/Chapter-4/Subchapter-III/9-421.03.xml","421.04":"Title-9/Chapter-4/Subchapter-III/9-421.04.xml","421.05":"Title-9/Chapter-4/Subchapter-III/9-421.05.xml","421.06":"Title-9/Chapter-4/Subchapter-III/9-421.06.xml","421.07":"Title-9/Chapter-4/Subchapter-III/9-421.07.xml","421.08":"Title-9/Chapter-4/Subchapter-III/9-421.08.xml","421.09":"Title-9/Chapter-4/Subchapter-III/9-421.09.xml","421.10":"Title-9/Chapter-4/Subchapter-III/9-421.10.xml","421.11":"Title-9/Chapter-4/Subchapter-III/9-421.11.xml","421.12":"Title-9/Chapter-4/Subchapter-III/9-421.12.xml","421.13":"Title-9/Chapter-4/Subchapter-III/9-421.13.xml","1201.01":"Title-9/Chapter-12/Subchapter-I/9-1201.01.xml","1201.02":"Title-9/Chapter-12/Subchapter-I/9-1201.02.xml","1201.03":"Title-9/Chapter-12/Subchapter-I/9-1201.03.xml","1201.04":"Title-9/Chapter-12/Subchapter-I/9-1201.04.xml","1201.05":"Title-9/Chapter-12/Subchapter-I/9-1201.05.xml","1201.06":"Title-9/Chapter-12/Subchapter-I/9-1201.06.xml","1201.07":"Title-9/Chapter-12/Subchapter-I/9-1201.07.xml","1201.08":"Title-9/Chapter-12/Subchapter-I/9-1201.08.xml","1201.09":"Title-9/Chapter-12/Subchapter-I/9-1201.09.xml","1201.10":"Title-9/Chapter-12/Subchapter-I/9-1201.10.xml","1201.11":"Title-9/Chapter-12/Subchapter-I/9-1201.11.xml","1201.12":"Title-9/Chapter-12/Subchapter-I/9-1201.12.xml","1201.13":"Title-9/Chapter-12/Subchapter-I/9-1201.13.xml","1201.14":"Title-9/Chapter-12/Subchapter-I/9-1201.14.xml","1201.15":"Title-9/Chapter-12/Subchapter-I/9-1201.15.xml","1205.01":"Title-9/Chapter-12/Subchapter-III/9-1205.01.xml","1205.02":"Title-9/Chapter-12/Subchapter-III/9-1205.02.xml","1205.03":"Title-9/Chapter-12/Subchapter-III/9-1205.03.xml","1205.04":"Title-9/Chapter-12/Subchapter-III/9-1205.04.xml","1205.05":"Title-9/Chapter-12/Subchapter-III/9-1205.05.xml","1203.01":"Title-9/Chapter-12/Subchapter-II/9-1203.01.xml","1203.02":"Title-9/Chapter-12/Subchapter-II/9-1203.02.xml","1203.03":"Title-9/Chapter-12/Subchapter-II/9-1203.03.xml","1203.04":"Title-9/Chapter-12/Subchapter-II/9-1203.04.xml","1203.05":"Title-9/Chapter-12/Subchapter-II/9-1203.05.xml","1203.06":"Title-9/Chapter-12/Subchapter-II/9-1203.06.xml","1203.07":"Title-9/Chapter-12/Subchapter-II/9-1203.07.xml","1203.08":"Title-9/Chapter-12/Subchapter-II/9-1203.08.xml","1203.09":"Title-9/Chapter-12/Subchapter-II/9-1203.09.xml","1208.01":"Title-9/Chapter-12/Subchapter-IV-A/9-1208.01.xml","1211.01":"Title-9/Chapter-12/Subchapter-VI/9-1211.01.xml","1207.01":"Title-9/Chapter-12/Subchapter-IV/9-1207.01.xml","1207.02":"Title-9/Chapter-12/Subchapter-IV/9-1207.02.xml","1207.03":"Title-9/Chapter-12/Subchapter-IV/9-1207.03.xml","1207.04":"Title-9/Chapter-12/Subchapter-IV/9-1207.04.xml","1207.05":"Title-9/Chapter-12/Subchapter-IV/9-1207.05.xml","1213.01":"Title-9/Chapter-12/Subchapter-VII/9-1213.01.xml","1213.02":"Title-9/Chapter-12/Subchapter-VII/9-1213.02.xml","1213.03":"Title-9/Chapter-12/Subchapter-VII/9-1213.03.xml","1213.04":"Title-9/Chapter-12/Subchapter-VII/9-1213.04.xml","1213.05":"Title-9/Chapter-12/Subchapter-VII/9-1213.05.xml","1209.01":"Title-9/Chapter-12/Subchapter-V/9-1209.01.xml","1209.02":"Title-9/Chapter-12/Subchapter-V/9-1209.02.xml","1209.03":"Title-9/Chapter-12/Subchapter-V/9-1209.03.xml","1209.04":"Title-9/Chapter-12/Subchapter-V/9-1209.04.xml","1215.01":"Title-9/Chapter-12/Subchapter-VIII/9-1215.01.xml","1215.02":"Title-9/Chapter-12/Subchapter-VIII/9-1215.02.xml","1215.03":"Title-9/Chapter-12/Subchapter-VIII/9-1215.03.xml","1215.04":"Title-9/Chapter-12/Subchapter-VIII/9-1215.04.xml","1215.05":"Title-9/Chapter-12/Subchapter-VIII/9-1215.05.xml","1215.06":"Title-9/Chapter-12/Subchapter-VIII/9-1215.06.xml","1215.07":"Title-9/Chapter-12/Subchapter-VIII/9-1215.07.xml","1215.08":"Title-9/Chapter-12/Subchapter-VIII/9-1215.08.xml","1101.01":"Title-9/Chapter-11/Subchapter-I/9-1101.01.xml","1105.01":"Title-9/Chapter-11/Subchapter-III/9-1105.01.xml","1105.02":"Title-9/Chapter-11/Subchapter-III/9-1105.02.xml","1105.03":"Title-9/Chapter-11/Subchapter-III/9-1105.03.xml","1103.01":"Title-9/Chapter-11/Subchapter-II/9-1103.01.xml","1103.02":"Title-9/Chapter-11/Subchapter-II/9-1103.02.xml","1103.03":"Title-9/Chapter-11/Subchapter-II/9-1103.03.xml","1103.04":"Title-9/Chapter-11/Subchapter-II/9-1103.04.xml","1103.05":"Title-9/Chapter-11/Subchapter-II/9-1103.05.xml","1103.06":"Title-9/Chapter-11/Subchapter-II/9-1103.06.xml","1103.07":"Title-9/Chapter-11/Subchapter-II/9-1103.07.xml","1107.01":"Title-9/Chapter-11/Subchapter-IV/9-1107.01.xml","1107.02":"Title-9/Chapter-11/Subchapter-IV/9-1107.02.xml","1107.03":"Title-9/Chapter-11/Subchapter-IV/9-1107.03.xml","1107.04":"Title-9/Chapter-11/Subchapter-IV/9-1107.04.xml","1107.05":"Title-9/Chapter-11/Subchapter-IV/9-1107.05.xml","1107.06":"Title-9/Chapter-11/Subchapter-IV/9-1107.06.xml","1107.07":"Title-9/Chapter-11/Subchapter-IV/9-1107.07.xml","1107.08":"Title-9/Chapter-11/Subchapter-IV/9-1107.08.xml","1107.09":"Title-9/Chapter-11/Subchapter-IV/9-1107.09.xml","1107.10":"Title-9/Chapter-11/Subchapter-IV/9-1107.10.xml","1107.11":"Title-9/Chapter-11/Subchapter-IV/9-1107.11.xml","1107.12":"Title-9/Chapter-11/Subchapter-IV/9-1107.12.xml","1117.01":"Title-9/Chapter-11/Subchapter-IX/9-1117.01.xml","1117.02":"Title-9/Chapter-11/Subchapter-IX/9-1117.02.xml","1117.03":"Title-9/Chapter-11/Subchapter-IX/9-1117.03.xml","1117.04":"Title-9/Chapter-11/Subchapter-IX/9-1117.04.xml","1117.05":"Title-9/Chapter-11/Subchapter-IX/9-1117.05.xml","1109.01":"Title-9/Chapter-11/Subchapter-V/9-1109.01.xml","1109.02":"Title-9/Chapter-11/Subchapter-V/9-1109.02.xml","1109.03":"Title-9/Chapter-11/Subchapter-V/9-1109.03.xml","1109.04":"Title-9/Chapter-11/Subchapter-V/9-1109.04.xml","1109.05":"Title-9/Chapter-11/Subchapter-V/9-1109.05.xml","1109.06":"Title-9/Chapter-11/Subchapter-V/9-1109.06.xml","1109.07":"Title-9/Chapter-11/Subchapter-V/9-1109.07.xml","1113.01":"Title-9/Chapter-11/Subchapter-VII/9-1113.01.xml","1113.02":"Title-9/Chapter-11/Subchapter-VII/9-1113.02.xml","1113.03":"Title-9/Chapter-11/Subchapter-VII/9-1113.03.xml","1113.04":"Title-9/Chapter-11/Subchapter-VII/9-1113.04.xml","1113.05":"Title-9/Chapter-11/Subchapter-VII/9-1113.05.xml","1113.06":"Title-9/Chapter-11/Subchapter-VII/9-1113.06.xml","1113.07":"Title-9/Chapter-11/Subchapter-VII/9-1113.07.xml","1111.01":"Title-9/Chapter-11/Subchapter-VI/9-1111.01.xml","1111.02":"Title-9/Chapter-11/Subchapter-VI/9-1111.02.xml","1111.03":"Title-9/Chapter-11/Subchapter-VI/9-1111.03.xml","1111.04":"Title-9/Chapter-11/Subchapter-VI/9-1111.04.xml","1111.05":"Title-9/Chapter-11/Subchapter-VI/9-1111.05.xml","1111.06":"Title-9/Chapter-11/Subchapter-VI/9-1111.06.xml","1111.07":"Title-9/Chapter-11/Subchapter-VI/9-1111.07~P.xml","1111.08":"Title-9/Chapter-11/Subchapter-VI/9-1111.08.xml","1111.09":"Title-9/Chapter-11/Subchapter-VI/9-1111.09.xml","1111.10":"Title-9/Chapter-11/Subchapter-VI/9-1111.10.xml","1111.11":"Title-9/Chapter-11/Subchapter-VI/9-1111.11.xml","1111.12":"Title-9/Chapter-11/Subchapter-VI/9-1111.12.xml","1111.13":"Title-9/Chapter-11/Subchapter-VI/9-1111.13.xml","1111.14":"Title-9/Chapter-11/Subchapter-VI/9-1111.14.xml","1111.15":"Title-9/Chapter-11/Subchapter-VI/9-1111.15.xml","1111.16":"Title-9/Chapter-11/Subchapter-VI/9-1111.16.xml","1111.17":"Title-9/Chapter-11/Subchapter-VI/9-1111.17.xml","1115.01":"Title-9/Chapter-11/Subchapter-VIII/9-1115.01.xml","1115.02":"Title-9/Chapter-11/Subchapter-VIII/9-1115.02.xml","1115.03":"Title-9/Chapter-11/Subchapter-VIII/9-1115.03.xml","1115.04":"Title-9/Chapter-11/Subchapter-VIII/9-1115.04.xml","1108.11":"Title-9/Chapter-11/Subchapter-IV-B/9-1108.11.xml","1108.01":"Title-9/Chapter-11/Subchapter-IV-A/9-1108.01.xml","1108.02":"Title-9/Chapter-11/Subchapter-IV-A/9-1108.02.xml","115.01":"Title-9/Chapter-1/Subchapter-VIII/Part-A/9-115.01.xml","115.02":"Title-9/Chapter-1/Subchapter-VIII/Part-A/9-115.02.xml","115.11":"Title-9/Chapter-1/Subchapter-VIII/Part-B/9-115.11.xml","107.01":"Title-9/Chapter-1/Subchapter-IV/Part-A/9-107.01.xml","107.02":"Title-9/Chapter-1/Subchapter-IV/Part-A/9-107.02.xml","107.03":"Title-9/Chapter-1/Subchapter-IV/Part-A/9-107.03.xml","107.04":"Title-9/Chapter-1/Subchapter-IV/Part-A/9-107.04.xml","107.51":"Title-9/Chapter-1/Subchapter-IV/Part-B/9-107.51.xml","107.52":"Title-9/Chapter-1/Subchapter-IV/Part-B/9-107.52.xml","107.53":"Title-9/Chapter-1/Subchapter-IV/Part-B/9-107.53.xml","107.54":"Title-9/Chapter-1/Subchapter-IV/Part-B/9-107.54.xml","107.55":"Title-9/Chapter-1/Subchapter-IV/Part-B/9-107.55.xml","107.56":"Title-9/Chapter-1/Subchapter-IV/Part-B/9-107.56.xml","107.57":"Title-9/Chapter-1/Subchapter-IV/Part-B/9-107.57.xml","107.58":"Title-9/Chapter-1/Subchapter-IV/Part-B/9-107.58.xml","107.59":"Title-9/Chapter-1/Subchapter-IV/Part-B/9-107.59.xml","107.60":"Title-9/Chapter-1/Subchapter-IV/Part-B/9-107.60.xml","107.61":"Title-9/Chapter-1/Subchapter-IV/Part-B/9-107.61.xml","107.62":"Title-9/Chapter-1/Subchapter-IV/Part-B/9-107.62.xml","201.01":"Title-9/Chapter-2/Unit-A/Subchapter-I/9-201.01.xml","202.01":"Title-9/Chapter-2/Unit-A/Subchapter-II/9-202.01.xml","202.02":"Title-9/Chapter-2/Unit-A/Subchapter-II/9-202.02.xml","202.03":"Title-9/Chapter-2/Unit-A/Subchapter-II/9-202.03.xml","202.04":"Title-9/Chapter-2/Unit-A/Subchapter-II/9-202.04.xml","202.05":"Title-9/Chapter-2/Unit-A/Subchapter-II/9-202.05.xml","202.06":"Title-9/Chapter-2/Unit-A/Subchapter-II/9-202.06.xml","202.07":"Title-9/Chapter-2/Unit-A/Subchapter-II/9-202.07.xml","202.08":"Title-9/Chapter-2/Unit-A/Subchapter-II/9-202.08.xml","202.09":"Title-9/Chapter-2/Unit-A/Subchapter-II/9-202.09.xml","202.10":"Title-9/Chapter-2/Unit-A/Subchapter-II/9-202.10.xml","202.11":"Title-9/Chapter-2/Unit-A/Subchapter-II/9-202.11.xml","202.12":"Title-9/Chapter-2/Unit-A/Subchapter-II/9-202.12.xml","202.13":"Title-9/Chapter-2/Unit-A/Subchapter-II/9-202.13.xml","202.14":"Title-9/Chapter-2/Unit-A/Subchapter-II/9-202.14.xml","202.15":"Title-9/Chapter-2/Unit-A/Subchapter-II/9-202.15.xml","205.01":"Title-9/Chapter-2/Unit-A/Subchapter-V/9-205.01~P.xml","203.01":"Title-9/Chapter-2/Unit-A/Subchapter-III/9-203.01.xml","203.02":"Title-9/Chapter-2/Unit-A/Subchapter-III/9-203.02.xml","203.03":"Title-9/Chapter-2/Unit-A/Subchapter-III/9-203.03.xml","203.04":"Title-9/Chapter-2/Unit-A/Subchapter-III/9-203.04.xml","203.05":"Title-9/Chapter-2/Unit-A/Subchapter-III/9-203.05.xml","203.06":"Title-9/Chapter-2/Unit-A/Subchapter-III/9-203.06.xml","203.07":"Title-9/Chapter-2/Unit-A/Subchapter-III/9-203.07.xml","203.08":"Title-9/Chapter-2/Unit-A/Subchapter-III/9-203.08.xml","203.09":"Title-9/Chapter-2/Unit-A/Subchapter-III/9-203.09.xml","206.01":"Title-9/Chapter-2/Unit-A/Subchapter-VI/9-206.01.xml","206.02":"Title-9/Chapter-2/Unit-A/Subchapter-VI/9-206.02.xml","431.01":"Title-9/Chapter-4/Subchapter-IV/Part-A/9-431.01.xml","431.02":"Title-9/Chapter-4/Subchapter-IV/Part-A/9-431.02.xml","433.01":"Title-9/Chapter-4/Subchapter-IV/Part-B/9-433.01.xml","433.02":"Title-9/Chapter-4/Subchapter-IV/Part-B/9-433.02.xml","1217.01":"Title-9/Chapter-12/Subchapter-IX/Part-A/9-1217.01.xml","1217.11":"Title-9/Chapter-12/Subchapter-IX/Part-B/9-1217.11~P.xml","1217.29":"Title-9/Chapter-12/Subchapter-IX/Part-B/9-1217.29~P.xml","1219.01":"Title-9/Chapter-12/Subchapter-X/Part-A/9-1219.01.xml","1219.29":"Title-9/Chapter-12/Subchapter-X/Part-B/9-1219.29~P.xml","1219.32":"Title-9/Chapter-12/Subchapter-X/Part-B/9-1219.32~P.xml","1219.33":"Title-9/Chapter-12/Subchapter-X/Part-B/9-1219.33~P.xml","1219.40":"Title-9/Chapter-12/Subchapter-X/Part-B/9-1219.40~P.xml","1219.41":"Title-9/Chapter-12/Subchapter-X/Part-B/9-1219.41~P.xml","204.11":"Title-9/Chapter-2/Unit-A/Subchapter-IV/Part-B/9-204.11.xml","204.12":"Title-9/Chapter-2/Unit-A/Subchapter-IV/Part-B/9-204.12.xml","204.13":"Title-9/Chapter-2/Unit-A/Subchapter-IV/Part-B/9-204.13.xml","204.14":"Title-9/Chapter-2/Unit-A/Subchapter-IV/Part-B/9-204.14.xml","204.15":"Title-9/Chapter-2/Unit-A/Subchapter-IV/Part-B/9-204.15.xml","204.16":"Title-9/Chapter-2/Unit-A/Subchapter-IV/Part-B/9-204.16.xml","204.17":"Title-9/Chapter-2/Unit-A/Subchapter-IV/Part-B/9-204.17.xml","204.18":"Title-9/Chapter-2/Unit-A/Subchapter-IV/Part-B/9-204.18.xml","204.19":"Title-9/Chapter-2/Unit-A/Subchapter-IV/Part-B/9-204.19.xml","204.01":"Title-9/Chapter-2/Unit-A/Subchapter-IV/Part-A/9-204.01.xml","204.02":"Title-9/Chapter-2/Unit-A/Subchapter-IV/Part-A/9-204.02.xml","204.03":"Title-9/Chapter-2/Unit-A/Subchapter-IV/Part-A/9-204.03.xml","204.03a":"Title-9/Chapter-2/Unit-A/Subchapter-IV/Part-A/9-204.03a.xml","204.04":"Title-9/Chapter-2/Unit-A/Subchapter-IV/Part-A/9-204.04.xml","204.05":"Title-9/Chapter-2/Unit-A/Subchapter-IV/Part-A/9-204.05.xml","204.06":"Title-9/Chapter-2/Unit-A/Subchapter-IV/Part-A/9-204.06.xml","204.07":"Title-9/Chapter-2/Unit-A/Subchapter-IV/Part-A/9-204.07.xml","204.08":"Title-9/Chapter-2/Unit-A/Subchapter-IV/Part-A/9-204.08.xml","204.09":"Title-9/Chapter-2/Unit-A/Subchapter-IV/Part-A/9-204.09.xml"}}